tsformatter/__init__.py
tsformatter/py.typed
tsformatter-0.2.3.dist-info/LICENSE
tsformatter-0.2.3.dist-info/METADATA
tsformatter-0.2.3.dist-info/WHEEL
tsformatter-0.2.3.dist-info/top_level.txt
tsformatter-0.2.3.dist-info/RECORD
