Metadata-Version: 2.2
Name: tsformatter
Version: 0.2.3
Summary: Helper package to format TeamSpeak BBCode
Author: jykob
Project-URL: Homepage, https://github.com/jykob/tsformatter
Classifier: Programming Language :: Python :: 3
Classifier: License :: OSI Approved :: MIT License
Classifier: Operating System :: OS Independent
Requires-Python: >=3.8
License-File: LICENSE
Provides-Extra: dev
Requires-Dist: ruff>=0.4.4; extra == "dev"
Requires-Dist: pyright>=1.1.362; extra == "dev"
Provides-Extra: tests
Requires-Dist: pytest==8.1.1; extra == "tests"
